<Session title="PUZZLE_MESS_060.BMG">
  <Sentence id="0">
    <Commands>
      <Command>AA==</Command>
    </Commands>
    <Original>[0]</Original>
    <Translation>
    </Translation>
  </Sentence>
  <Sentence id="1">
    <Commands>
      <Command>GgYAAAwBChoWAAANAQDjgqLjgrfjg6Xjg6zjgqQKGgUAAA4K</Command>
      <Command>ChoFAAABChoWAAANAQDjgqLjgrfjg6Xjg6zjgqQKGgUAAA4K</Command>
      <Command>Cg==</Command>
      <Command>ChoFAAABCgA=</Command>
    </Commands>
    <Original>[0]"Judd's documents are no longer necessary.[1]Your last task is to find information relating to[2]mnemonic fluid."[3]</Original>
    <Translation>[0]"贾德的文档应该不需要了。[1]你最后的任务是找到[2]关于记忆流转的信息。”[3]</Translation>
  </Sentence>
  <Sentence id="2">
    <Commands>
      <Command>AA==</Command>
    </Commands>
    <Original>[0]</Original>
    <Translation>
    </Translation>
  </Sentence>
  <Sentence id="3">
    <Commands>
      <Command>AA==</Command>
    </Commands>
    <Original>[0]</Original>
    <Translation>
    </Translation>
  </Sentence>
  <Sentence id="4">
    <Commands>
      <Command>AA==</Command>
    </Commands>
    <Original>[0]</Original>
    <Translation>
    </Translation>
  </Sentence>
  <Sentence id="5">
    <Commands>
      <Command>AA==</Command>
    </Commands>
    <Original>[0]</Original>
    <Translation>
    </Translation>
  </Sentence>
  <Sentence id="6">
    <Commands>
      <Command>AAAAAAAAAAAAAAAAAAAAAAAAAAAAAA==</Command>
    </Commands>
    <Original>[0]</Original>
    <Translation>
    </Translation>
  </Sentence>
</Session>